brickblock/__init__.py
brickblock/__test_api.py
brickblock/__test_api_builder.py
brickblock/__test_api_pydantic.py
brickblock/__test_api_with_file.py
brickblock/bb.py
brickblock/abstract/__init__.py
brickblock/api/__init__.py
brickblock/api/api_handler.py
brickblock/api/api_handler_legacy.py
brickblock/deploy/__init__.py
brickblock/function/__init__.py
brickblock/function/base_function.py
brickblock/pipeline/__init__.py
brickblock/pipeline/base_pipeline.py
brickblock/templates/__init__.py
brickblock/utils/__init__.py
brickblock/utils/model_serializer.py
brickblock/workflow/__init__.py
brickblock/workflow/base_workflow.py
bb_core-0.3.2.dist-info/METADATA
bb_core-0.3.2.dist-info/WHEEL
bb_core-0.3.2.dist-info/top_level.txt
bb_core-0.3.2.dist-info/RECORD
