Metadata-Version: 2.2
Name: bb-core
Version: 0.3.2
Summary: Core package for the brickblock library.
Home-page: https://github.com/erfanvaredi/brickblock
Author: Erfan
Author-email: erfanvaredi@gmail.com
Classifier: Programming Language :: Python :: 3
Classifier: License :: OSI Approved :: MIT License
Classifier: Operating System :: OS Independent
Requires-Python: >=3.10
Dynamic: author
Dynamic: author-email
Dynamic: classifier
Dynamic: description
Dynamic: description-content-type
Dynamic: home-page
Dynamic: requires-python
Dynamic: summary
